cold_call/__init__.py
cold_call-0.1.0.dist-info/METADATA
cold_call-0.1.0.dist-info/WHEEL
cold_call-0.1.0.dist-info/licenses/LICENSE.txt
cold_call-0.1.0.dist-info/RECORD
