Metadata-Version: 2.1
Name: cold-call
Version: 0.1.0
Summary: Give Python functions your unsolicited input
Project-URL: Documentation, https://github.com/bernardcooke53/cold-call#readme
Project-URL: Issues, https://github.com/bernardcooke53/cold-call/issues
Project-URL: Source, https://github.com/bernardcooke53/cold-call
Author-email: Bernard Cooke <bernard-cooke@hotmail.com>
License-Expression: MIT
License-File: LICENSE.txt
Classifier: Development Status :: 4 - Beta
Classifier: Programming Language :: Python
Classifier: Programming Language :: Python :: 3.8
Classifier: Programming Language :: Python :: 3.9
Classifier: Programming Language :: Python :: 3.10
Classifier: Programming Language :: Python :: 3.11
Classifier: Programming Language :: Python :: 3.12
Classifier: Programming Language :: Python :: Implementation :: CPython
Classifier: Programming Language :: Python :: Implementation :: PyPy
Requires-Python: >=3.8
